{
  "Возраст": "",
  "Город": "",
  "Данные не указаны": "",
  "Заполните поле ввода Username": "",
  "Имя": "",
  "Имя и Фамилия обязательны": "",
  "Имя пользователя": "",
  "Некорректная ссылка на фото профиля": "",
  "Некорректный возраст": "",
  "Некорректный город": "",
  "Отменить": "",
  "Попробуйте обновить страницу": "",
  "Произошла ошибка при загрузке данных": "",
  "Профиль": "",
  "Редактировать": "",
  "Серверная ошибка при сохранении": "",
  "Сохранить": "",
  "Укажите валюту": "",
  "Укажите страну": "",
  "Фамилия": "",
  "Фото профиля": ""
}
